hlpl_press/__init__.py
hlpl_press/__main__.py
hlpl_press/setup.cfg
hlpl_press/uc.png
hlpl_press-1.0.4.dist-info/LICENSE
hlpl_press-1.0.4.dist-info/METADATA
hlpl_press-1.0.4.dist-info/WHEEL
hlpl_press-1.0.4.dist-info/entry_points.txt
hlpl_press-1.0.4.dist-info/top_level.txt
hlpl_press-1.0.4.dist-info/RECORD
